COPYING
README.md
instance/__init__.py
instance/config.py
instance/docker.py
instance/production.py.cfg
runserver.py
statsservice/__init__.py
statsservice/api/v1/__init__.py
statsservice/api/v1/client.py
statsservice/api/v1/common.py
statsservice/api/v1/identity.py
statsservice/api/v1/processed.py
statsservice/api/v1/stats.py
statsservice/bootstrap.py
statsservice/commands/__init__.py
statsservice/commands/client.py
statsservice/commands/database.py
statsservice/commands/mosp.py
statsservice/commands/stats.py
statsservice/lib/__init__.py
statsservice/lib/mosp.py
statsservice/lib/processors.py
statsservice/lib/utils.py
statsservice/lib/validation.py
statsservice/models/__init__.py
statsservice/models/client.py
statsservice/models/stats.py
statsservice/static/.gitkeep
statsservice/static/css/custom.css
statsservice/static/img/apple-touch-icon.png
statsservice/static/img/favicon.ico
statsservice/static/img/monarc-logo.png
statsservice/static/img/stats-service-logo.png
statsservice/static/img/stats-service-logo.xcf
statsservice/static/js/evolutionCharts.js
statsservice/static/js/map.js
statsservice/static/js/risksCharts.js
statsservice/static/js/threatsCharts.js
statsservice/static/js/utils.js
statsservice/static/js/vulnerabilitiesCharts.js
statsservice/templates/about.html
statsservice/templates/about_more.html
statsservice/templates/evolution.html
statsservice/templates/help.html
statsservice/templates/human.txt
statsservice/templates/index.html
statsservice/templates/layout.html
statsservice/templates/map.html
statsservice/translations/babel.cfg
statsservice/translations/extract.sh
statsservice/translations/fr_FR/LC_MESSAGES/messages.po
statsservice/translations/messages.pot
statsservice/views/__init__.py
statsservice/views/admin.py
statsservice/views/common.py
statsservice/views/map.py
statsservice/views/root.py
statsservice/views/stats.py
statsservice-0.5.2.dist-info/entry_points.txt
statsservice-0.5.2.dist-info/COPYING
statsservice-0.5.2.dist-info/WHEEL
statsservice-0.5.2.dist-info/METADATA
statsservice-0.5.2.dist-info/RECORD
