Metadata-Version: 2.1
Name: statsservice
Version: 0.5.2
Summary: Stats Service for MONARC.
Home-page: https://github.com/monarc-project/stats-service
License: AGPL-3.0-or-later
Keywords: monarc,security,stats,flask,api
Author: Cédric Bonhomme
Author-email: cedric@cedricbonhomme.org
Requires-Python: >=3.8,<3.11
Classifier: Development Status :: 5 - Production/Stable
Classifier: Environment :: Web Environment
Classifier: License :: OSI Approved :: GNU Affero General Public License v3 or later (AGPLv3+)
Classifier: Operating System :: OS Independent
Classifier: Programming Language :: Python :: 3
Classifier: Programming Language :: Python :: 3.10
Classifier: Programming Language :: Python :: 3.8
Classifier: Programming Language :: Python :: 3.9
Classifier: Topic :: Security
Requires-Dist: Flask (>=2.0.2,<3.0.0)
Requires-Dist: Flask-Babel (>=2.0.0,<3.0.0)
Requires-Dist: Flask-Migrate (>=3.1.0,<4.0.0)
Requires-Dist: Flask-SQLAlchemy (>=2.5.1,<3.0.0)
Requires-Dist: alembic (>=1.7.7,<2.0.0)
Requires-Dist: flask_login (>=0.6.1,<0.7.0)
Requires-Dist: flask_principal (>=0.4.0,<0.5.0)
Requires-Dist: flask_restx (>=0.5.1,<0.6.0)
Requires-Dist: jsonschema (>=3.2.0,<4.0.0)
Requires-Dist: mypy (>=0.950,<0.951)
Requires-Dist: packaging (>=21.3,<22.0)
Requires-Dist: psycopg2-binary (>=2.9.3,<3.0.0)
Requires-Dist: pymosp (>=0.4.2,<0.5.0)
Requires-Dist: python-dateutil (>=2.8.2,<3.0.0)
Requires-Dist: requests (>=2.25.1,<3.0.0)
Requires-Dist: types-python-dateutil (>=2.8.15,<3.0.0)
Requires-Dist: types-requests (>=2.27.25,<3.0.0)
Requires-Dist: types-setuptools (>=57.4.14,<58.0.0)
Requires-Dist: typing-extensions (>=4.2.0,<5.0.0)
Requires-Dist: werkzeug (==2.0.3)
Project-URL: Documentation, https://www.monarc.lu/documentation/stats-service
Project-URL: Repository, https://github.com/monarc-project/stats-service
